LICENSE.rst
MANIFEST.in
NOTICE.rst
README.rst
setup.py
twitter_oauth.html
twitter_oauth.py
twitter_oauth.egg-info/PKG-INFO
twitter_oauth.egg-info/SOURCES.txt
twitter_oauth.egg-info/dependency_links.txt
twitter_oauth.egg-info/requires.txt
twitter_oauth.egg-info/top_level.txt