Metadata-Version: 1.0
Name: twitter-oauth
Version: 0.1.0
Summary: A Python module for Twitter API and OAuth
Home-page: http://code.google.com/p/twitter-oauth
Author: Kenko
Author-email: kenko.py@gmail.com
License: MIT License
Keywords: Twitter,Oauth
Platform: UNKNOWN
Classifier: Programming Language :: Python
Classifier: Topic :: Software Development :: Libraries :: Python Modules
